safeme/__init__.py
safeme/api.py
safeme/cli.py
safeme/core/__init__.py
safeme/core/ddos.py
safeme/core/firewall.py
safeme/core/integrity.py
safeme/core/ssh.py
safeme/core/sysctl.py
safeme/core/utils.py
safeme-0.1.4.dist-info/licenses/LICENSE
safeme-0.1.4.dist-info/METADATA
safeme-0.1.4.dist-info/WHEEL
safeme-0.1.4.dist-info/entry_points.txt
safeme-0.1.4.dist-info/top_level.txt
safeme-0.1.4.dist-info/RECORD
