Metadata-Version: 2.4
Name: SafeMe
Version: 0.1.4
Summary: One-command backend Linux server security: firewall, SSH hardening, DDoS protection, integrity checks and more.
Home-page: https://github.com/prakhardoneria/safeme
Author: Prakhar Doneria
Author-email: prakhardoneria3@gmail.com
License: MIT
Project-URL: Homepage, https://github.com/prakhardoneria/safeme
Project-URL: Repository, https://github.com/prakhardoneria/safeme
Project-URL: Issues, https://github.com/prakhardoneria/safeme/issues
Classifier: Programming Language :: Python :: 3
Classifier: License :: OSI Approved :: MIT License
Classifier: Operating System :: POSIX :: Linux
Requires-Python: >=3.7
License-File: LICENSE
Requires-Dist: typer[all]
Dynamic: author
Dynamic: author-email
Dynamic: classifier
Dynamic: description
Dynamic: description-content-type
Dynamic: home-page
Dynamic: license
Dynamic: license-file
Dynamic: project-url
Dynamic: requires-dist
Dynamic: requires-python
Dynamic: summary
